<r>
  <e>
    <lg>
      <l pos="N">adopsjovne</l>
    </lg>
    <tg lang="sv">
      <t pos="N">adoption</t>
    </tg>
    <tg lang="nb">
      <t pos="N">adopsjon</t>
    </tg>
    <orig>Adopsjovne, (S) adopsjon (nb), adoption (sv)</orig>
  </e>
  <e>
    <lg>
      <l pos="V">adopteeredh</l>
    </lg>
    <tg lang="sv">
      <t pos="V">adoptere</t>
    </tg>
    <tg lang="nb">
      <t pos="V">adoptere</t>
    </tg>
    <orig>Adopteeredh, (V) adoptere (nb), adoptere (sv)</orig>
  </e>
  <e>
    <lg>
      <l pos="Phrase">aeriebadtje (attr)</l>
    </lg>
    <tg lang="sv">
      <t pos="Phrase">tidigare</t>
    </tg>
    <tg lang="nb">
      <t pos="Phrase">tidligere</t>
    </tg>
    <orig>Aeriebadtje (attr), (A) tidligere (nb), tidigare (sv)</orig>
  </e>
  <e>
    <lg>
      <l pos="N">aerpiegïele</l>
    </lg>
    <tg lang="eng">
      <t pos="N">heritage language</t>
    </tg>
    <tg lang="sv">
      <t pos="N">arvspråk</t>
    </tg>
    <tg lang="nb">
      <t pos="N">arvspråk</t>
    </tg>
    <orig>Aerpiegïele, (S) arvspråk (nb), arvspråk (sv), heritage language (eng)</orig>
  </e>
  <e>
    <lg>
      <l pos="Phrase">aerpiegïelen soptsestæjja</l>
    </lg>
    <tg lang="sv">
      <t pos="Phrase">arvspråkstalare</t>
    </tg>
    <tg lang="nb">
      <t pos="Phrase">arvspråkstaler</t>
    </tg>
    <orig>Aerpiegïelen soptsestæjja, (MWE) arvspråkstaler (nb), arvspråkstalare (sv)</orig>
  </e>
  <e>
    <lg>
      <l pos="N">almadahke</l>
    </lg>
    <tg lang="sv">
      <t pos="N">rymden</t>
    </tg>
    <tg lang="nb">
      <t pos="N">verdensrom</t>
    </tg>
    <orig>Almadahke, (S), verdensrom (nb), rymden (sv)</orig>
  </e>
  <e>
    <lg>
      <l pos="V">annoteeredh</l>
    </lg>
    <tg lang="sv">
      <t pos="V">annotera</t>
    </tg>
    <tg lang="nb">
      <t pos="V">annotere</t>
    </tg>
    <tg lang="nb">
      <t pos="V">notere</t>
    </tg>
    <tg lang="nb">
      <t pos="V">anmerke</t>
    </tg>
    <orig>Annoteeredh, (V) annotere, notere, anmerke (nb), annotera (sv)</orig>
  </e>
  <e>
    <lg>
      <l pos="A">attribuhtijve</l>
    </lg>
    <tg lang="sv">
      <t pos="A">attributiv</t>
    </tg>
    <tg lang="nb">
      <t pos="A">attributiv</t>
    </tg>
    <orig>Attribuhtijve, (A) attributiv (nb), attributiv (sv)</orig>
  </e>
  <e>
    <lg>
      <l pos="N">baanghke</l>
    </lg>
    <tg lang="sv">
      <t pos="N">bank</t>
    </tg>
    <tg lang="nb">
      <t pos="N">bank</t>
    </tg>
    <orig>Baanghke, (S) bank (nb), bank (sv)</orig>
  </e>
  <e>
    <lg>
      <l pos="N">bacheloretjaalaldahke</l>
    </lg>
    <tg lang="sv">
      <t pos="N">uppsats</t>
    </tg>
    <tg lang="nb">
      <t pos="N">bacheloroppgave</t>
    </tg>
    <orig>Bacheloretjaalaldahke, (S) bacheloroppgave (nb), uppsats (sv)</orig>
  </e>
  <e>
    <lg>
      <l pos="N">barkoemojhtese</l>
    </lg>
    <tg lang="sv">
      <t pos="N">arbetsminne</t>
    </tg>
    <tg lang="nb">
      <t pos="N">arbeidsminne</t>
    </tg>
    <tg lang="nb">
      <t pos="N">korttidshukommelse</t>
    </tg>
    <orig>Barkoemojhtese, (S) arbeidsminne, korttidshukommelse (nb), arbetsminne (sv)</orig>
  </e>
  <e>
    <lg>
      <l pos="N">bealasadtje</l>
    </lg>
    <tg lang="sv">
      <t pos="N">jävig person</t>
    </tg>
    <tg lang="nb">
      <t pos="N">inhabil person</t>
    </tg>
    <orig>Bealasadtje, (S) inhabil person (nb), jävig person (sv)</orig>
  </e>
  <e>
    <lg>
      <l pos="N">biejjiecelle</l>
    </lg>
    <tg lang="sv">
      <t pos="N">solcell</t>
    </tg>
    <tg lang="nb">
      <t pos="N">solcelle</t>
    </tg>
    <orig>Biejjiecelle, (S) solcelle (nb), solcell (sv)</orig>
  </e>
  <e>
    <lg>
      <l pos="N">biejjiefaamoe</l>
    </lg>
    <tg lang="sv">
      <t pos="N">solkraft</t>
    </tg>
    <tg lang="nb">
      <t pos="N">solkraft</t>
    </tg>
    <orig>Biejjiefaamoe, (S) solkraft (nb), solkraft (sv)</orig>
  </e>
  <e>
    <lg>
      <l pos="N">bïenje-vuejeme</l>
    </lg>
    <tg lang="sv">
      <t pos="N">hundspann</t>
    </tg>
    <tg lang="nb">
      <t pos="N">hundekjøring</t>
    </tg>
    <orig>Bïenje-vuejeme, (S) hundekjøring (nb) hundspann (sv)</orig>
  </e>
  <e>
    <lg>
      <l pos="N">bijjielïhtse</l>
    </lg>
    <tg lang="sv">
      <t pos="N">överledd</t>
    </tg>
    <tg lang="nb">
      <t pos="N">overledd</t>
    </tg>
    <orig>Bijjielïhtse, (S) overledd (nb), överledd (sv)</orig>
  </e>
  <e>
    <lg>
      <l pos="N">bïjle-beelhkehtse</l>
    </lg>
    <tg lang="sv">
      <t pos="N">bilvrak</t>
    </tg>
    <tg lang="nb">
      <t pos="N">bilvrak</t>
    </tg>
    <orig>Bïjle-beelhkehtse, (S) bilvrak (nb), bilvrak (sv)</orig>
  </e>
  <e>
    <lg>
      <l pos="Phrase">bitnehtidh transitivt verb</l>
    </lg>
    <tg lang="sv">
      <t pos="Phrase">dränka</t>
    </tg>
    <tg lang="nb">
      <t pos="Phrase">drenke</t>
    </tg>
    <tg lang="nb">
      <t pos="Phrase">drukne (noe)</t>
    </tg>
    <orig>Bitnehtidh transitivt verb, (V) drenke, drukne (noe) (nb), dränka (sv)</orig>
  </e>
  <e>
    <lg>
      <l pos="Phrase">bovvestalledh (passiv)</l>
    </lg>
    <tg lang="sv">
      <t pos="Phrase">bli dräpt</t>
    </tg>
    <tg lang="nb">
      <t pos="Phrase">å bli drept</t>
    </tg>
    <orig>Bovvestalledh (passiv), (V) å bli drept (nb) bli dräpt (sv)</orig>
  </e>
  <e>
    <lg>
      <l pos="V">daejriehtidh</l>
    </lg>
    <tg lang="sv">
      <t pos="V">betyda</t>
    </tg>
    <tg lang="nb">
      <t pos="V">å betyde</t>
    </tg>
    <orig>Daejriehtidh, (V) å betyde (nb), betyda (sv)</orig>
  </e>
  <e>
    <lg>
      <l pos="N">diblemevuekie</l>
    </lg>
    <tg lang="sv">
      <t pos="N">härskateknik</t>
    </tg>
    <tg lang="nb">
      <t pos="N">hersketeknikk</t>
    </tg>
    <orig>Diblemevuekie, (S) hersketeknikk (nb), härskateknik (sv)</orig>
  </e>
  <e>
    <lg>
      <l pos="A">dïedteguedtije</l>
    </lg>
    <tg lang="sv">
      <t pos="A">ansvarig</t>
    </tg>
    <tg lang="nb">
      <t pos="A">ansvarlig</t>
    </tg>
    <orig>Dïedteguedtije, (A) ansvarlig (nb), ansvarig (sv)</orig>
  </e>
  <e>
    <lg>
      <l pos="N">dïejvese</l>
    </lg>
    <tg lang="sv">
      <t pos="N">begrepp som beteckning</t>
    </tg>
    <tg lang="sv">
      <t pos="N">ordspråk</t>
    </tg>
    <tg lang="nb">
      <t pos="N">begrep som betegnelse</t>
    </tg>
    <tg lang="nb">
      <t pos="N">ordtak</t>
    </tg>
    <orig>Dïejvese, (S) begrep som betegnelse, ordtak (nb), begrepp som beteckning, ordspråk (sv)</orig>
  </e>
  <e>
    <lg>
      <l pos="V">dievhtedh</l>
    </lg>
    <tg lang="sv">
      <t pos="V">tanka (bil)</t>
    </tg>
    <tg lang="nb">
      <t pos="V">å tanke (bil)</t>
    </tg>
    <orig>Dievhtedh, (V) å tanke (bil) (nb), tanka (bil) (sv)</orig>
  </e>
  <e>
    <lg>
      <l pos="N">dorjeldh-jiermie</l>
    </lg>
    <tg lang="sv">
      <l_ref>digijiermie_n</l_ref>
      <t pos="N">artificiell intelligens</t>
    </tg>
    <tg lang="nb">
      <l_ref>digijiermie_n</l_ref>
      <t pos="N">kunstig intelligens</t>
    </tg>
    <orig>Dorjeldh-jiermie, digijiermie, (S) kunstig intelligens (nb), artificiell intelligens (sv)</orig>
  </e>
  <e>
    <lg>
      <l pos="N">digijiermie</l>
    </lg>
    <tg lang="sv">
      <l_ref>dorjeldh-jiermie_n</l_ref>
      <t pos="N">artificiell intelligens</t>
    </tg>
    <tg lang="nb">
      <l_ref>dorjeldh-jiermie_n</l_ref>
      <t pos="N">kunstig intelligens</t>
    </tg>
    <orig>Dorjeldh-jiermie, digijiermie, (S) kunstig intelligens (nb), artificiell intelligens (sv)</orig>
  </e>
  <e>
    <lg>
      <l pos="N">duekie</l>
    </lg>
    <tg lang="sv">
      <t pos="N">bakgrund</t>
    </tg>
    <tg lang="nb">
      <t pos="N">bakgrunn</t>
    </tg>
    <orig>Duekie, (S) bakgrunn (nb), bakgrund (sv)</orig>
  </e>
  <e>
    <lg>
      <l pos="N">dåakteretjaalaldahke</l>
    </lg>
    <tg lang="sv">
      <t pos="N">doktorsavhandling</t>
    </tg>
    <tg lang="nb">
      <t pos="N">doktoravhandling</t>
    </tg>
    <orig>Dåakteretjaalaldahke, (S) doktoravhandling (nb), doktorsavhandling (sv)</orig>
  </e>
  <e>
    <lg>
      <l pos="A">dåeriesfaages</l>
    </lg>
    <tg lang="nb">
      <t pos="A">tverrfaglig</t>
    </tg>
    <orig>Dåeriesfaages, (A) tverrfaglig (nb)</orig>
  </e>
  <e>
    <lg>
      <l pos="N">eatnemeravra</l>
    </lg>
    <tg lang="sv">
      <t pos="N">jordklot</t>
    </tg>
    <tg lang="nb">
      <t pos="N">jordklode</t>
    </tg>
    <orig>Eatnemeravra, (S) jordklode (nb), jordklot (sv)</orig>
  </e>
  <e>
    <lg>
      <l pos="A">empatije</l>
    </lg>
    <tg lang="sv">
      <t pos="A">medlidande</t>
    </tg>
    <tg lang="sv">
      <t pos="A">empati</t>
    </tg>
    <tg lang="nb">
      <t pos="A">medfølelse</t>
    </tg>
    <tg lang="nb">
      <t pos="A">empati</t>
    </tg>
    <orig>Empatije, (A) medfølelse, empati (nb), medlidande, empati (sv)</orig>
  </e>
  <e>
    <lg>
      <l pos="N">empirije</l>
    </lg>
    <tg lang="sv">
      <t pos="N">empiri</t>
    </tg>
    <tg lang="nb">
      <t pos="N">empiri</t>
    </tg>
    <orig>Empirije, (S) empiri (nb), empiri (sv)</orig>
  </e>
  <e>
    <lg>
      <l pos="N">feadtagïele</l>
    </lg>
    <tg lang="sv">
      <t pos="N">inhemska språk</t>
    </tg>
    <tg lang="nb">
      <t pos="N">innfødt språk</t>
    </tg>
    <orig>Feadtagïele, (S) innfødt språk (nb), inhemska språk (sv)</orig>
  </e>
  <e>
    <lg>
      <l pos="N">gaarhkesbaante</l>
    </lg>
    <tg lang="sv">
      <t pos="N">spännband</t>
    </tg>
    <tg lang="nb">
      <t pos="N">spennbånd</t>
    </tg>
    <tg lang="nb">
      <t pos="N">lastespenner</t>
    </tg>
    <orig>Gaarhkesbaante, (S) Spennbånd, lastespenner (nb) spännband (sv)</orig>
  </e>
  <e>
    <lg>
      <l pos="N">gabre</l>
    </lg>
    <tg lang="sv">
      <t pos="N">kapuschong</t>
    </tg>
    <tg lang="nb">
      <t pos="N">hette</t>
    </tg>
    <orig>Gabre, (S) hette (nb) kapuschong (sv)</orig>
  </e>
  <e>
    <lg>
      <l pos="V">jårrelidh</l>
    </lg>
    <tg lang="sv">
      <l_ref>gaengkerestedh_v</l_ref>
      <t pos="V">hjula</t>
    </tg>
    <tg lang="nb">
      <l_ref>gaengkerestedh_v</l_ref>
      <t pos="V">slå hjul</t>
    </tg>
    <orig>Gaengkerestedh, jårrelidh, (V) slå hjul (nb), hjula (sv)</orig>
  </e>
  <e>
    <lg>
      <l pos="V">gaengkerestedh</l>
    </lg>
    <tg lang="sv">
      <l_ref>jårrelidh_v</l_ref>
      <t pos="V">hjula</t>
    </tg>
    <tg lang="nb">
      <l_ref>jårrelidh_v</l_ref>
      <t pos="V">slå hjul</t>
    </tg>
    <orig>Gaengkerestedh, jårrelidh, (V) slå hjul (nb), hjula (sv)</orig>
  </e>
  <e>
    <lg>
      <l pos="V">gieltedh</l>
    </lg>
    <tg lang="sv">
      <t pos="V">ladda något (t ex telefon)</t>
    </tg>
    <tg lang="nb">
      <t pos="V">å lade noe (feks telefon)</t>
    </tg>
    <orig>Gieltedh, (V) Å lade noe (feks telefon) (nb), ladda något (t ex telefon) (sv)</orig>
  </e>
  <e>
    <lg>
      <l pos="N">gieltemestasjovne</l>
    </lg>
    <tg lang="nb">
      <t pos="N">ladestasjon</t>
    </tg>
    <orig>Gieltemestasjovne, (S) Ladestasjon (nb)</orig>
  </e>
  <e>
    <lg>
      <l pos="N">gïetetjaalege</l>
    </lg>
    <tg lang="sv">
      <t pos="N">manuskript</t>
    </tg>
    <tg lang="nb">
      <t pos="N">manuskript</t>
    </tg>
    <orig>Gïetetjaalege, (S) manuskript (nb), manuskript (sv)</orig>
  </e>
  <e>
    <lg>
      <l pos="N">girtie-alaarme</l>
    </lg>
    <tg lang="sv">
      <t pos="N">flygalarm</t>
    </tg>
    <tg lang="nb">
      <t pos="N">flyalarm</t>
    </tg>
    <orig>Girtie-alaarme, (S) flyalarm (nb), flygalarm (sv)</orig>
  </e>
  <e>
    <lg>
      <l pos="Phrase">håvhnjode jårrelidh</l>
    </lg>
    <tg lang="sv">
      <l_ref>jårrelidh_v</l_ref>
      <t pos="Phrase">kullerbytta</t>
    </tg>
    <tg lang="nb">
      <l_ref>jårrelidh_v</l_ref>
      <t pos="Phrase">stupe kråke</t>
    </tg>
    <tg lang="nb">
      <l_ref>jårrelidh_v</l_ref>
      <t pos="Phrase">kollbøtte</t>
    </tg>
    <orig>Håvhnjode jårrelidh, jårrelidh, (V) Stupe kråke, kollbøtte (nb) kullerbytta (sv)</orig>
  </e>
  <e>
    <lg>
      <l pos="V">jårrelidh</l>
    </lg>
    <tg lang="sv">
      <l_ref>håvhnjode_jårrelidh_phrase</l_ref>
      <t pos="V">kullerbytta</t>
    </tg>
    <tg lang="nb">
      <l_ref>håvhnjode_jårrelidh_phrase</l_ref>
      <t pos="V">stupe kråke</t>
    </tg>
    <tg lang="nb">
      <l_ref>håvhnjode_jårrelidh_phrase</l_ref>
      <t pos="V">kollbøtte</t>
    </tg>
    <orig>Håvhnjode jårrelidh, jårrelidh, (V) Stupe kråke, kollbøtte (nb) kullerbytta (sv)</orig>
  </e>
  <e>
    <lg>
      <l pos="V">ïedtjestalledh</l>
    </lg>
    <tg lang="sv">
      <t pos="V">engagera sig</t>
    </tg>
    <tg lang="nb">
      <t pos="V">å engasjere seg (feks i foreningsarbeid)</t>
    </tg>
    <orig>Ïedtjestalledh, (V) å engasjere seg (feks i foreningsarbeid) (nb), engagera sig (sv)</orig>
  </e>
  <e>
    <lg>
      <l pos="N">intendeente</l>
    </lg>
    <tg lang="sv">
      <t pos="N">intendent</t>
    </tg>
    <tg lang="nb">
      <t pos="N">intendent</t>
    </tg>
    <orig>Intendeente, (S) intendent (nb), intendent (sv)</orig>
  </e>
  <e>
    <lg>
      <l pos="N">jïengegaamegh</l>
    </lg>
    <tg lang="sv">
      <t pos="N">brodder</t>
    </tg>
    <tg lang="nb">
      <t pos="N">piggsko</t>
    </tg>
    <tg lang="nb">
      <t pos="N">brodda</t>
    </tg>
    <orig>Jïengegaamegh, (S) piggsko, brodda (nb) brodder (sv)</orig>
  </e>
  <e>
    <lg>
      <l pos="A">jïjtjeraarh</l>
    </lg>
    <tg lang="sv">
      <l_ref>jïjtjeraadh_(attr)_jïjtjeraarehke_phrase</l_ref>
      <l_ref>jïjtjeraadehke_(pred)_phrase</l_ref>
      <t pos="A">självständig</t>
    </tg>
    <tg lang="nb">
      <l_ref>jïjtjeraadh_(attr)_jïjtjeraarehke_phrase</l_ref>
      <l_ref>jïjtjeraadehke_(pred)_phrase</l_ref>
      <t pos="A">selvstendig</t>
    </tg>
    <orig>jïjtjeraarh, jïjtjeraadh (attr), jïjtjeraarehke, jïjtjeraadehke (pred), (A) selvstendig (nb), självständig (sv)</orig>
  </e>
  <e>
    <lg>
      <l pos="Phrase">jïjtjeraadh (attr) jïjtjeraarehke</l>
    </lg>
    <tg lang="sv">
      <l_ref>jïjtjeraarh_a</l_ref>
      <l_ref>jïjtjeraadehke_(pred)_phrase</l_ref>
      <t pos="Phrase">självständig</t>
    </tg>
    <tg lang="nb">
      <l_ref>jïjtjeraarh_a</l_ref>
      <l_ref>jïjtjeraadehke_(pred)_phrase</l_ref>
      <t pos="Phrase">selvstendig</t>
    </tg>
    <orig>jïjtjeraarh, jïjtjeraadh (attr), jïjtjeraarehke, jïjtjeraadehke (pred), (A) selvstendig (nb), självständig (sv)</orig>
  </e>
  <e>
    <lg>
      <l pos="Phrase">jïjtjeraadehke (pred)</l>
    </lg>
    <tg lang="sv">
      <l_ref>jïjtjeraarh_a</l_ref>
      <l_ref>jïjtjeraadh_(attr)_jïjtjeraarehke_phrase</l_ref>
      <t pos="Phrase">självständig</t>
    </tg>
    <tg lang="nb">
      <l_ref>jïjtjeraarh_a</l_ref>
      <l_ref>jïjtjeraadh_(attr)_jïjtjeraarehke_phrase</l_ref>
      <t pos="Phrase">selvstendig</t>
    </tg>
    <orig>jïjtjeraarh, jïjtjeraadh (attr), jïjtjeraarehke, jïjtjeraadehke (pred), (A) selvstendig (nb), självständig (sv)</orig>
  </e>
  <e>
    <lg>
      <l pos="N">komplemente</l>
    </lg>
    <tg lang="sv">
      <t pos="N">komplemenet</t>
    </tg>
    <tg lang="nb">
      <t pos="N">den styrte termen</t>
    </tg>
    <tg lang="nb">
      <t pos="N">komplement</t>
    </tg>
    <orig>Komplemente, (S) den styrte termen, komplement (nb), komplemenet (sv)</orig>
  </e>
  <e>
    <lg>
      <l pos="N">kopulagaatoe</l>
    </lg>
    <tg lang="nb">
      <t pos="N">uteblivelse av kopula</t>
    </tg>
    <orig>Kopulagaatoe, (S) uteblivelse av kopula (nb)</orig>
  </e>
  <e>
    <lg>
      <l pos="N">laageguejmie</l>
    </lg>
    <tg lang="sv">
      <t pos="N">lagkompis</t>
    </tg>
    <tg lang="sv">
      <t pos="N">medspelare</t>
    </tg>
    <tg lang="nb">
      <t pos="N">lagkamerat</t>
    </tg>
    <tg lang="nb">
      <t pos="N">medspiller</t>
    </tg>
    <orig>Laageguejmie, (S) lagkamerat, medspiller (nb) lagkompis, medspelare (sv)</orig>
  </e>
  <e>
    <lg>
      <l pos="N">laageåvtehke</l>
    </lg>
    <tg lang="sv">
      <t pos="N">lagkapten</t>
    </tg>
    <tg lang="nb">
      <t pos="N">lagkaptein</t>
    </tg>
    <orig>Laageåvtehke, (S) lagkaptein (nb) lagkapten (sv)</orig>
  </e>
  <e>
    <lg>
      <l pos="N">laantemïerhke</l>
    </lg>
    <tg lang="sv">
      <t pos="N">landmärke</t>
    </tg>
    <tg lang="nb">
      <t pos="N">landemerke</t>
    </tg>
    <orig>Laantemïerhke, (S) landemerke (nb), landmärke (sv)</orig>
  </e>
  <e>
    <lg>
      <l pos="N">laavkome-åålja</l>
    </lg>
    <tg lang="sv">
      <t pos="N">badolja</t>
    </tg>
    <tg lang="nb">
      <t pos="N">badeolje</t>
    </tg>
    <orig>Laavkome-åålja, (S) badeolje (nb), badolja (sv)</orig>
  </e>
  <e>
    <lg>
      <l pos="N">lahtese</l>
    </lg>
    <tg lang="sv">
      <t pos="N">begrepp som benämning</t>
    </tg>
    <tg lang="nb">
      <t pos="N">begrep som benevnelse</t>
    </tg>
    <orig>Lahtese, (S) begrep som benevnelse (nb) begrepp som benämning (sv)</orig>
  </e>
  <e>
    <lg>
      <l pos="Phrase">lajvedh iv</l>
    </lg>
    <tg lang="sv">
      <t pos="Phrase">försvinna (smärta sjukdom)</t>
    </tg>
    <tg lang="nb">
      <t pos="Phrase">forsvinne</t>
    </tg>
    <tg lang="nb">
      <t pos="Phrase">gå over (i smerte</t>
    </tg>
    <tg lang="nb">
      <t pos="Phrase">sykdom)</t>
    </tg>
    <orig>Lajvedh IV, (V) forsvinne, gå over (i smerte, sykdom) (nb), försvinna (smärta, sjukdom) (sv)</orig>
  </e>
  <e>
    <lg>
      <l pos="N">lissiebïevnese</l>
    </lg>
    <tg lang="sv">
      <t pos="N">ytterligare information</t>
    </tg>
    <tg lang="nb">
      <t pos="N">tilleggsopplysning</t>
    </tg>
    <tg lang="nb">
      <t pos="N">kuriositet</t>
    </tg>
    <orig>Lissiebïevnese, (S) tilleggsopplysning, kuriositet (nb), ytterligare information (sv)</orig>
  </e>
  <e>
    <lg>
      <l pos="V">lotjkehtalledh</l>
    </lg>
    <tg lang="sv">
      <t pos="V">förhandla och komma överens</t>
    </tg>
    <tg lang="nb">
      <t pos="V">forhandle og komme til enighet</t>
    </tg>
    <orig>Lotjkehtalledh, (V) Forhandle og komme til enighet (nb) förhandla och komma överens (sv)</orig>
  </e>
  <e>
    <lg>
      <l pos="V">lutniestidh</l>
    </lg>
    <tg lang="sv">
      <t pos="V">frikänna</t>
    </tg>
    <tg lang="nb">
      <t pos="V">frifinne</t>
    </tg>
    <tg lang="nb">
      <t pos="V">frikjenne</t>
    </tg>
    <orig>Lutniestidh, (V) frifinne, frikjenne (nb), frikänna (sv)</orig>
  </e>
  <e>
    <lg>
      <l pos="V">lutniestovvedh</l>
    </lg>
    <tg lang="sv">
      <t pos="V">bli frikänt</t>
    </tg>
    <tg lang="nb">
      <t pos="V">bli frikjent</t>
    </tg>
    <tg lang="nb">
      <t pos="V">bli frifunnet</t>
    </tg>
    <orig>Lutniestovvedh, (V) bli frikjent, bli frifunnet (nb) , bli frikänt (sv)</orig>
  </e>
  <e>
    <lg>
      <l pos="N">læhla</l>
    </lg>
    <tg lang="sv">
      <t pos="N">björnunge</t>
    </tg>
    <tg lang="nb">
      <t pos="N">bjørnunge</t>
    </tg>
    <orig>Læhla, (S) bjørnunge (nb), björnunge (sv)</orig>
  </e>
  <e>
    <lg>
      <l pos="N">maarhtebïenje</l>
    </lg>
    <tg lang="lat">
      <t pos="N">nyctereutes procyonides</t>
    </tg>
    <tg lang="sv">
      <t pos="N">mårdhund</t>
    </tg>
    <tg lang="nb">
      <t pos="N">mårhund</t>
    </tg>
    <orig>Maarhtebïenje, (S) mårhund (nb), mårdhund (sv), nyctereutes procyonides (lat)</orig>
  </e>
  <e>
    <lg>
      <l pos="N">maasteretjaalaldahke</l>
    </lg>
    <tg lang="nb">
      <t pos="N">masteravhandling</t>
    </tg>
    <orig>Maasteretjaalaldahke, (S) masteravhandling (nb)</orig>
  </e>
  <e>
    <lg>
      <l pos="V">mietiehtidh</l>
    </lg>
    <tg lang="sv">
      <t pos="V">erkänne</t>
    </tg>
    <tg lang="nb">
      <t pos="V">erkjenne</t>
    </tg>
    <orig>Mietiehtidh, (V) erkjenne (nb), erkänne (sv)</orig>
  </e>
  <e>
    <lg>
      <l pos="V">minngiedidh</l>
    </lg>
    <tg lang="sv">
      <t pos="V">utsätta</t>
    </tg>
    <tg lang="nb">
      <t pos="V">å utsette</t>
    </tg>
    <orig>Minngiedidh, (V) å utsette (nb), utsätta (sv)</orig>
  </e>
  <e>
    <lg>
      <l pos="A">mööktege</l>
    </lg>
    <tg lang="sv">
      <t pos="A">näringsrik</t>
    </tg>
    <tg lang="nb">
      <t pos="A">næringsrik</t>
    </tg>
    <orig>Mööktege, (A) næringsrik (nb) näringsrik (sv)</orig>
  </e>
  <e>
    <lg>
      <l pos="N">naalhbolle</l>
    </lg>
    <tg lang="sv">
      <t pos="N">sjöborre</t>
    </tg>
    <tg lang="nb">
      <t pos="N">kråkeboller</t>
    </tg>
    <tg lang="nb">
      <t pos="N">sjøpiggsvin</t>
    </tg>
    <tg lang="nb">
      <t pos="N">sjøpinnsvin</t>
    </tg>
    <orig>Naalhbolle, (S) Kråkeboller, sjøpiggsvin, sjøpinnsvin (nb), sjöborre (sv)</orig>
  </e>
  <e>
    <lg>
      <l pos="N">neblie</l>
    </lg>
    <tg lang="sv">
      <t pos="N">hätta</t>
    </tg>
    <tg lang="nb">
      <t pos="N">liten lue</t>
    </tg>
    <orig>Neblie, (S) liten lue (nb), hätta (sv)</orig>
  </e>
  <e>
    <lg>
      <l pos="N">njålhtjome-jievege</l>
    </lg>
    <tg lang="sv">
      <l_ref>trampolijne_n</l_ref>
      <t pos="N">stutsmatte</t>
    </tg>
    <tg lang="nb">
      <l_ref>trampolijne_n</l_ref>
      <t pos="N">trampoline</t>
    </tg>
    <orig>Njålhtjome-jievege, trampolijne, (S) Trampoline (nb) stutsmatte (sv)</orig>
  </e>
  <e>
    <lg>
      <l pos="N">trampolijne</l>
    </lg>
    <tg lang="sv">
      <l_ref>njålhtjome-jievege_n</l_ref>
      <t pos="N">stutsmatte</t>
    </tg>
    <tg lang="nb">
      <l_ref>njålhtjome-jievege_n</l_ref>
      <t pos="N">trampoline</t>
    </tg>
    <orig>Njålhtjome-jievege, trampolijne, (S) Trampoline (nb) stutsmatte (sv)</orig>
  </e>
  <e>
    <lg>
      <l pos="N">nueliesïeve</l>
    </lg>
    <tg lang="eng">
      <t pos="N">underline</t>
    </tg>
    <tg lang="sv">
      <t pos="N">understreck</t>
    </tg>
    <tg lang="sv">
      <t pos="N">golvstreck</t>
    </tg>
    <tg lang="sv">
      <t pos="N">markstreck</t>
    </tg>
    <tg lang="nb">
      <t pos="N">understrek</t>
    </tg>
    <orig>Nueliesïeve, (S) understrek (nb) understreck, golvstreck , markstreck (sv), underline (eng)</orig>
  </e>
  <e>
    <lg>
      <l pos="N">nænnoestahke</l>
    </lg>
    <tg lang="sv">
      <t pos="N">beslut</t>
    </tg>
    <tg lang="nb">
      <t pos="N">vedtak</t>
    </tg>
    <orig>Nænnoestahke, (S) vedtak (nb) beslut (sv)</orig>
  </e>
  <e>
    <lg>
      <l pos="N">ovmessievoete</l>
    </lg>
    <tg lang="sv">
      <t pos="N">olikhet</t>
    </tg>
    <tg lang="nb">
      <t pos="N">forskjellighet</t>
    </tg>
    <tg lang="nb">
      <t pos="N">ulikhet</t>
    </tg>
    <orig>Ovmessievoete, (S) forskjellighet, ulikhet (nb), olikhet (sv)</orig>
  </e>
  <e>
    <lg>
      <l pos="A">ov-våajnoes</l>
    </lg>
    <tg lang="sv">
      <t pos="A">osynlig</t>
    </tg>
    <tg lang="nb">
      <t pos="A">usynlig</t>
    </tg>
    <orig>Ov-våajnoes, (A) Usynlig (nb) osynlig (sv)</orig>
  </e>
  <e>
    <lg>
      <l pos="N">plaaste</l>
    </lg>
    <tg lang="sv">
      <t pos="N">plast</t>
    </tg>
    <tg lang="nb">
      <t pos="N">plastikk</t>
    </tg>
    <orig>Plaaste, (S) plastikk (nb), plast (sv)</orig>
  </e>
  <e>
    <lg>
      <l pos="N">prostaate</l>
    </lg>
    <tg lang="sv">
      <t pos="N">prostata</t>
    </tg>
    <tg lang="nb">
      <t pos="N">prostata</t>
    </tg>
    <orig>Prostaate, (S) prostata (nb), prostata (sv)</orig>
  </e>
  <e>
    <lg>
      <l pos="N">raagkese</l>
    </lg>
    <tg lang="sv">
      <t pos="N">sovtält</t>
    </tg>
    <tg lang="nb">
      <t pos="N">sovetelt</t>
    </tg>
    <orig>Raagkese, (S) sovetelt, (nb) sovtält (sv)</orig>
  </e>
  <e>
    <lg>
      <l pos="N">raastedåapmere</l>
    </lg>
    <tg lang="sv">
      <t pos="N">linjedomare</t>
    </tg>
    <tg lang="nb">
      <t pos="N">linjedommer</t>
    </tg>
    <orig>Raastedåapmere, (S) linjedommer (nb) linjedomare (sv)</orig>
  </e>
  <e>
    <lg>
      <l pos="N">landslag</l>
    </lg>
    <tg lang="sv">
      <l_ref>rïjhkelaage_n</l_ref>
      <t pos="N">landslag</t>
    </tg>
    <orig>Rïjhkelaage, (S) landslag, (S) landslag (sv)</orig>
  </e>
  <e>
    <lg>
      <l pos="N">rïjhkelaage</l>
    </lg>
    <tg lang="sv">
      <l_ref>landslag_n</l_ref>
      <t pos="N">landslag</t>
    </tg>
    <orig>Rïjhkelaage, (S) landslag, (S) landslag (sv)</orig>
  </e>
  <e>
    <lg>
      <l pos="Phrase">råatjkoeh (attr) råatjkoen (pred)</l>
    </lg>
    <tg lang="sv">
      <l_ref>råatjkoes_a</l_ref>
      <t pos="Phrase">cynisk</t>
    </tg>
    <tg lang="nb">
      <l_ref>råatjkoes_a</l_ref>
      <t pos="Phrase">kynisk</t>
    </tg>
    <orig>Råatjkoes, råatjkoeh (attr), Råatjkoen (pred), (A) kynisk (nb), cynisk (sv)</orig>
  </e>
  <e>
    <lg>
      <l pos="A">råatjkoes</l>
    </lg>
    <tg lang="sv">
      <l_ref>råatjkoeh_(attr)_råatjkoen_(pred)_phrase</l_ref>
      <t pos="A">cynisk</t>
    </tg>
    <tg lang="nb">
      <l_ref>råatjkoeh_(attr)_råatjkoen_(pred)_phrase</l_ref>
      <t pos="A">kynisk</t>
    </tg>
    <orig>Råatjkoes, råatjkoeh (attr), Råatjkoen (pred), (A) kynisk (nb), cynisk (sv)</orig>
  </e>
  <e>
    <lg>
      <l pos="V">saarkodh</l>
    </lg>
    <tg lang="sv">
      <t pos="V">skissera</t>
    </tg>
    <tg lang="sv">
      <t pos="V">teckna</t>
    </tg>
    <tg lang="nb">
      <t pos="V">å skissere</t>
    </tg>
    <tg lang="nb">
      <t pos="V">tegne</t>
    </tg>
    <orig>Saarkodh, (V) å skissere, tegne (nb), skissera, teckna (sv)</orig>
  </e>
  <e>
    <lg>
      <l pos="Phrase">saktedh iv</l>
    </lg>
    <tg lang="sv">
      <t pos="Phrase">sugen på något speciellt</t>
    </tg>
    <tg lang="nb">
      <t pos="Phrase">tørste etter noe spesielt</t>
    </tg>
    <orig>Saktedh IV, (V) tørste etter noe spesielt (nb), sugen på något speciellt (sv)</orig>
  </e>
  <e>
    <lg>
      <l pos="Phrase">sirtedh trans</l>
    </lg>
    <tg lang="sv">
      <l_ref>sertedh_v</l_ref>
      <t pos="Phrase">förflytta</t>
    </tg>
    <tg lang="nb">
      <l_ref>sertedh_v</l_ref>
      <t pos="Phrase">omplassere</t>
    </tg>
    <orig>Sertedh, sirtedh trans, (V) omplassere (nb), förflytta (sv)</orig>
  </e>
  <e>
    <lg>
      <l pos="V">sertedh</l>
    </lg>
    <tg lang="sv">
      <l_ref>sirtedh_trans_phrase</l_ref>
      <t pos="V">förflytta</t>
    </tg>
    <tg lang="nb">
      <l_ref>sirtedh_trans_phrase</l_ref>
      <t pos="V">omplassere</t>
    </tg>
    <orig>Sertedh, sirtedh trans, (V) omplassere (nb), förflytta (sv)</orig>
  </e>
  <e>
    <lg>
      <l pos="N">sprijnehtasse</l>
    </lg>
    <tg lang="sv">
      <t pos="N">avvikelse</t>
    </tg>
    <tg lang="nb">
      <t pos="N">avvik</t>
    </tg>
    <orig>Sprijnehtasse, (S) avvik (nb), avvikelse (sv)</orig>
  </e>
  <e>
    <lg>
      <l pos="N">staabe</l>
    </lg>
    <tg lang="sv">
      <t pos="N">stab</t>
    </tg>
    <tg lang="nb">
      <t pos="N">stab</t>
    </tg>
    <orig>Staabe, (S) stab (nb), stab (sv)</orig>
  </e>
  <e>
    <lg>
      <l pos="N">thetakriterije</l>
    </lg>
    <tg lang="sv">
      <t pos="N">thetakriteriet</t>
    </tg>
    <tg lang="nb">
      <t pos="N">thetakriteriet</t>
    </tg>
    <orig>Thetakriterije, (S) thetakriteriet (nb), thetakriteriet (sv)</orig>
  </e>
  <e>
    <lg>
      <l pos="N">thetarolle</l>
    </lg>
    <tg lang="sv">
      <t pos="N">thetaroll</t>
    </tg>
    <tg lang="nb">
      <t pos="N">thetarolle</t>
    </tg>
    <orig>Thetarolle, (S) thetarolle (nb), thetaroll (sv)</orig>
  </e>
  <e>
    <lg>
      <l pos="N">thetaviermie</l>
    </lg>
    <tg lang="sv">
      <t pos="N">thetagrid</t>
    </tg>
    <tg lang="nb">
      <t pos="N">thetagrid</t>
    </tg>
    <orig>Thetaviermie, (S) thetagrid (nb) thetagrid (sv)</orig>
  </e>
  <e>
    <lg>
      <l pos="N">tjaalaldahke</l>
    </lg>
    <tg lang="sv">
      <t pos="N">avhandling</t>
    </tg>
    <tg lang="nb">
      <t pos="N">avhandling</t>
    </tg>
    <orig>Tjaalaldahke, (S) avhandling (nb), avhandling (sv)</orig>
  </e>
  <e>
    <lg>
      <l pos="N">tjalsehkh</l>
    </lg>
    <tg lang="sv">
      <l_ref>sjæjsah_n</l_ref>
      <t pos="N">skridskor</t>
    </tg>
    <tg lang="nb">
      <l_ref>sjæjsah_n</l_ref>
      <t pos="N">skøyter</t>
    </tg>
    <orig>Tjalsehkh, sjæjsah, (S) skøyter (nb), skridskor (sv)</orig>
  </e>
  <e>
    <lg>
      <l pos="N">sjæjsah</l>
    </lg>
    <tg lang="sv">
      <l_ref>tjalsehkh_n</l_ref>
      <t pos="N">skridskor</t>
    </tg>
    <tg lang="nb">
      <l_ref>tjalsehkh_n</l_ref>
      <t pos="N">skøyter</t>
    </tg>
    <orig>Tjalsehkh, sjæjsah, (S) skøyter (nb), skridskor (sv)</orig>
  </e>
  <e>
    <lg>
      <l pos="Phrase">tjïektjestalledh (passiv)</l>
    </lg>
    <tg lang="sv">
      <t pos="Phrase">bli sparkad</t>
    </tg>
    <tg lang="nb">
      <t pos="Phrase">å bli sparket</t>
    </tg>
    <orig>Tjïektjestalledh (passiv), (V) å bli sparket (nb), bli sparkad (sv)</orig>
  </e>
  <e>
    <lg>
      <l pos="N">tjoejemålsome</l>
    </lg>
    <tg lang="sv">
      <t pos="N">omljud</t>
    </tg>
    <tg lang="nb">
      <t pos="N">omlyd</t>
    </tg>
    <orig>Tjoejemålsome, (S) omlyd (nb), omljud (sv)</orig>
  </e>
  <e>
    <lg>
      <l pos="N">vierhkievierhtie</l>
    </lg>
    <tg lang="sv">
      <l_ref>tsevtsvierhtie_n</l_ref>
      <t pos="N">handlingsmedel</t>
    </tg>
    <tg lang="nb">
      <l_ref>tsevtsvierhtie_n</l_ref>
      <t pos="N">virkemiddel</t>
    </tg>
    <orig>Vierhkievierhtie, tsevtsvierhtie, (S) virkemiddel (nb), handlingsmedel (sv)</orig>
  </e>
  <e>
    <lg>
      <l pos="N">tsevtsvierhtie</l>
    </lg>
    <tg lang="sv">
      <l_ref>vierhkievierhtie_n</l_ref>
      <t pos="N">handlingsmedel</t>
    </tg>
    <tg lang="nb">
      <l_ref>vierhkievierhtie_n</l_ref>
      <t pos="N">virkemiddel</t>
    </tg>
    <orig>Vierhkievierhtie, tsevtsvierhtie, (S) virkemiddel (nb), handlingsmedel (sv)</orig>
  </e>
  <e>
    <lg>
      <l pos="N">vijriedahke</l>
    </lg>
    <tg lang="sv">
      <t pos="N">utsträckning</t>
    </tg>
    <tg lang="nb">
      <t pos="N">utstrekning</t>
    </tg>
    <orig>Vijriedahke, (S) utstrekning (nb), utsträckning (sv)</orig>
  </e>
  <e>
    <lg>
      <l pos="V">voejhkeladtedh</l>
    </lg>
    <tg lang="sv">
      <t pos="V">experimentera</t>
    </tg>
    <tg lang="nb">
      <t pos="V">eksperimentere</t>
    </tg>
    <orig>Voejhkeladtedh, (V) eksperimentere (nb), experimentera (sv)</orig>
  </e>
  <e>
    <lg>
      <l pos="Phrase">voelkehtidh transitivt verb</l>
    </lg>
    <tg lang="sv">
      <t pos="Phrase">kidnappa</t>
    </tg>
    <tg lang="nb">
      <t pos="Phrase">kidnappe</t>
    </tg>
    <orig>Voelkehtidh transitivt verb, (V) kidnappe (nb), kidnappa (sv)</orig>
  </e>
  <e>
    <lg>
      <l pos="V">voelkehtovvedh</l>
    </lg>
    <tg lang="sv">
      <t pos="V">bli kidnappat</t>
    </tg>
    <tg lang="nb">
      <t pos="V">bli kidnappet</t>
    </tg>
    <orig>Voelkehtovvedh, (V) bli kidnappet (nb), bli kidnappat (sv)</orig>
  </e>
  <e>
    <lg>
      <l pos="Phrase">vuajahtalledh (passiv)</l>
    </lg>
    <tg lang="sv">
      <t pos="Phrase">bli påkört</t>
    </tg>
    <tg lang="nb">
      <t pos="Phrase">bli påkjørt</t>
    </tg>
    <orig>Vuajahtalledh (passiv), (V) bli påkjørt (nb) bli påkört (sv)</orig>
  </e>
  <e>
    <lg>
      <l pos="N">vuelielïhtse</l>
    </lg>
    <tg lang="sv">
      <t pos="N">nedre led</t>
    </tg>
    <tg lang="nb">
      <t pos="N">underledd</t>
    </tg>
    <orig>Vuelielïhtse, (S) underledd (nb), nedre led (sv)</orig>
  </e>
  <e>
    <lg>
      <l pos="Phrase">våaroehtidh transitivt verb</l>
    </lg>
    <tg lang="sv">
      <t pos="Phrase">prioritera</t>
    </tg>
    <tg lang="sv">
      <t pos="Phrase">främja</t>
    </tg>
    <tg lang="sv">
      <t pos="Phrase">gynna</t>
    </tg>
    <tg lang="sv">
      <t pos="Phrase">föredra</t>
    </tg>
    <tg lang="nb">
      <t pos="Phrase">prioritere</t>
    </tg>
    <orig>Våaroehtidh transitivt verb, (V) prioritere (nb), prioritera, främja, gynna, föredra (sv)</orig>
  </e>
  <e>
    <lg>
      <l pos="A">åavtoes</l>
    </lg>
    <tg lang="sv">
      <t pos="A">mystisk</t>
    </tg>
    <tg lang="nb">
      <t pos="A">mystisk</t>
    </tg>
    <tg lang="nb">
      <t pos="A">underlig</t>
    </tg>
    <orig>Åavtoes, (A) mystisk, underlig (nb), mystisk (sv)</orig>
  </e>
  <e>
    <lg>
      <l pos="N">årroehbïjle</l>
    </lg>
    <tg lang="sv">
      <t pos="N">campingbil</t>
    </tg>
    <tg lang="sv">
      <t pos="N">husbil</t>
    </tg>
    <tg lang="nb">
      <t pos="N">bobil</t>
    </tg>
    <tg lang="nb">
      <t pos="N">campingbil</t>
    </tg>
    <orig>Årroehbïjle, (S) Bobil, campingbil (nb), campingbil, husbil (sv)</orig>
  </e>
  <e>
    <lg>
      <l pos="N">årroehvåågne</l>
    </lg>
    <tg lang="sv">
      <t pos="N">husvagn</t>
    </tg>
    <tg lang="nb">
      <t pos="N">husvogn</t>
    </tg>
    <tg lang="nb">
      <t pos="N">campingvogn</t>
    </tg>
    <orig>Årroehvåågne, (S) husvogn, campingvogn (nb), husvagn (sv)</orig>
  </e>
  <e>
    <lg>
      <l pos="N">ååljaprutnie</l>
    </lg>
    <tg lang="sv">
      <t pos="N">oljebrunn</t>
    </tg>
    <tg lang="nb">
      <t pos="N">oljebrønn</t>
    </tg>
    <orig>Ååljaprutnie, (S) oljebrønn (nb), oljebrunn (sv)</orig>
  </e>
  <e>
    <lg>
      <l pos="N">ååljatseagkere</l>
    </lg>
    <tg lang="sv">
      <t pos="N">oljerigg</t>
    </tg>
    <tg lang="nb">
      <t pos="N">oljerigg</t>
    </tg>
    <orig>Ååljatseagkere, (S) oljerigg (nb), oljerigg (sv)</orig>
  </e>
  <e>
    <lg>
      <l pos="N">åålmehjaahkoe</l>
    </lg>
    <tg lang="sv">
      <t pos="N">folktro</t>
    </tg>
    <tg lang="nb">
      <t pos="N">folketro</t>
    </tg>
    <orig>Åålmehjaahkoe, (S) folketro (nb), folktro (sv)</orig>
  </e>
  <e>
    <lg>
      <l pos="N">automasjovne-ingenjööre</l>
    </lg>
    <tg lang="sv">
      <t pos="N">automationsingenjör</t>
    </tg>
    <tg lang="nb">
      <t pos="N">automasjonsingeniør</t>
    </tg>
    <orig>Automasjovne-ingenjööre, (S) automasjonsingeniør (nb), automationsingenjör (sv)</orig>
  </e>
  <e>
    <lg>
      <l pos="N">automasjovneteknihkere</l>
    </lg>
    <tg lang="sv">
      <t pos="N">automationstekniker</t>
    </tg>
    <tg lang="nb">
      <t pos="N">automasjonstekniker</t>
    </tg>
    <orig>Automasjovneteknihkere, (S) automasjonstekniker (nb), automationstekniker (sv)</orig>
  </e>
  <e>
    <lg>
      <l pos="Phrase">barkiji- jïh maahtoegoevtese</l>
    </lg>
    <tg lang="sv">
      <t pos="Phrase">enheten för personal och kompetens</t>
    </tg>
    <orig>Barkiji- jïh maahtoegoevtese, (S) enheten för personal och kompetens (sv)</orig>
  </e>
  <e>
    <lg>
      <l pos="N">barkoemaarhna-goevtese</l>
    </lg>
    <tg lang="sv">
      <t pos="N">arbetsmarknadsenhet</t>
    </tg>
    <tg lang="nb">
      <t pos="N">arbeidsmarkedenhet</t>
    </tg>
    <orig>Barkoemaarhna-goevtese, (S) arbeidsmarkedenhet (nb) arbetsmarknadsenhet (sv)</orig>
  </e>
  <e>
    <lg>
      <l pos="N">beapmoe-baatsehts</l>
    </lg>
    <tg lang="sv">
      <l_ref>beapmoe-baatsehtasse_n</l_ref>
      <t pos="N">matavfall</t>
    </tg>
    <tg lang="nb">
      <l_ref>beapmoe-baatsehtasse_n</l_ref>
      <t pos="N">matavfall</t>
    </tg>
    <orig>Beapmoe-baatsehts, beapmoe-baatsehtasse, (S) matavfall (nb), matavfall (sv)</orig>
  </e>
  <e>
    <lg>
      <l pos="N">beapmoe-baatsehtasse</l>
    </lg>
    <tg lang="sv">
      <l_ref>beapmoe-baatsehts_n</l_ref>
      <t pos="N">matavfall</t>
    </tg>
    <tg lang="nb">
      <l_ref>beapmoe-baatsehts_n</l_ref>
      <t pos="N">matavfall</t>
    </tg>
    <orig>Beapmoe-baatsehts, beapmoe-baatsehtasse, (S) matavfall (nb), matavfall (sv)</orig>
  </e>
  <e>
    <lg>
      <l pos="N">darjome-iktedæjja</l>
    </lg>
    <tg lang="sv">
      <t pos="N">aktivitetskoordinator</t>
    </tg>
    <orig>Darjome-iktedæjja, (S) aktivitetskoordinator (sv)</orig>
  </e>
  <e>
    <lg>
      <l pos="N">e-dïenesje</l>
    </lg>
    <tg lang="nb">
      <t pos="N">e-tjenester</t>
    </tg>
    <tg lang="sv">
      <t pos="N">e-tjänst</t>
    </tg>
    <orig>E-dïenesje, (S) E-tjänst (sv), E-tjenester (nb)</orig>
  </e>
  <e>
    <lg>
      <l pos="N">eejehtslehkie</l>
    </lg>
    <tg lang="sv">
      <t pos="N">semesterort</t>
    </tg>
    <tg lang="nb">
      <t pos="N">feriested</t>
    </tg>
    <orig>Eejehtslehkie, (S) feriested (nb) semesterort (sv)</orig>
  </e>
  <e>
    <lg>
      <l pos="N">eejehtsmehkie</l>
    </lg>
    <tg lang="nb">
      <t pos="N">ferietur</t>
    </tg>
    <orig>Eejehtsmehkie, (S) ferietur (nb)</orig>
  </e>
  <e>
    <lg>
      <l pos="N">eekeskaehtie</l>
    </lg>
    <tg lang="sv">
      <t pos="N">fastighetsskatt</t>
    </tg>
    <tg lang="nb">
      <t pos="N">eiendomsskatt</t>
    </tg>
    <orig>Eekeskaehtie, (S) eiendomsskatt (nb) fastighetsskatt (sv)</orig>
  </e>
  <e>
    <lg>
      <l pos="Phrase">energije- jïh daalhkadahkeraeriestæjja</l>
    </lg>
    <tg lang="sv">
      <t pos="Phrase">energi- och klimatrådgivare</t>
    </tg>
    <orig>Energije- jïh daalhkadahkeraeriestæjja, (S) Energi- och klimatrådgivare (sv)</orig>
  </e>
  <e>
    <lg>
      <l pos="N">fuelhkiereakta-goevtese</l>
    </lg>
    <tg lang="sv">
      <t pos="N">enhten för familjerätt</t>
    </tg>
    <orig>Fuelhkiereakta-goevtese, (S) enhten för familjerätt (sv)</orig>
  </e>
  <e>
    <lg>
      <l pos="Phrase">gaahpede jïjjem biejjiem</l>
    </lg>
    <tg lang="sv">
      <t pos="Phrase">dygnöppet</t>
    </tg>
    <tg lang="sv">
      <t pos="Phrase">24 7</t>
    </tg>
    <tg lang="nb">
      <t pos="Phrase">døgnbemannet</t>
    </tg>
    <orig>Gaahpede jïjjem biejjiem, (MWE) døgnbemannet (nb), dygnöppet, 24 7 (sv)</orig>
  </e>
  <e>
    <lg>
      <l pos="N">-geehtije</l>
    </lg>
    <tg lang="nb">
      <t pos="N">vaktmester</t>
    </tg>
    <tg lang="sv">
      <t pos="N">vaktmästare</t>
    </tg>
    <orig>-geehtije, (S) vaktmästare (sv), vaktmester (nb)</orig>
  </e>
  <e>
    <lg>
      <l pos="Phrase">geervealmetji goevtese</l>
    </lg>
    <tg lang="sv">
      <t pos="Phrase">enheten för vuxna</t>
    </tg>
    <orig>Geervealmetji goevtese, (S) enheten för vuxna (sv)</orig>
  </e>
  <e>
    <lg>
      <l pos="N">gohtjesööpije</l>
    </lg>
    <tg lang="nb">
      <t pos="N">feier</t>
    </tg>
    <tg lang="sv">
      <t pos="N">skorstensfejare</t>
    </tg>
    <tg lang="sv">
      <t pos="N">sotarmurre</t>
    </tg>
    <tg lang="sv">
      <t pos="N">sotare</t>
    </tg>
    <orig>Gohtjesööpije, (S) skorstensfejare, sotarmurre, sotare (sv) feier (nb)</orig>
  </e>
  <e>
    <lg>
      <l pos="N">gærhkoegaertenen-aamhtesereerije</l>
    </lg>
    <tg lang="sv">
      <t pos="N">kyrkogårdshandläggare</t>
    </tg>
    <orig>Gærhkoegaertenen-aamhtesereerije, (S) kyrkogårdshandläggare (sv)</orig>
  </e>
  <e>
    <lg>
      <l pos="N">gærhkoegaertenen-geehtije</l>
    </lg>
    <tg lang="sv">
      <t pos="N">kyrkogårdsvaktmästare</t>
    </tg>
    <orig>Gærhkoegaertenen-geehtije, (S) kyrkogårdsvaktmästare (sv)</orig>
  </e>
  <e>
    <lg>
      <l pos="N">gærhkoegaertenenåejvie</l>
    </lg>
    <tg lang="sv">
      <t pos="N">kyrkogårdschef</t>
    </tg>
    <orig>Gærhkoegaertenenåejvie, (S) kyrkogårdschef (sv)</orig>
  </e>
  <e>
    <lg>
      <l pos="N">gærhkoegaertene-tjåadtjoehtæjja</l>
    </lg>
    <tg lang="sv">
      <t pos="N">kyrkogårdsföreståndare</t>
    </tg>
    <orig>Gærhkoegaertene-tjåadtjoehtæjja, (S) kyrkogårdsföreståndare (sv)</orig>
  </e>
  <e>
    <lg>
      <l pos="N">gærkoegaertenen-reereme</l>
    </lg>
    <tg lang="sv">
      <t pos="N">kyrkogårdsförvaltning</t>
    </tg>
    <orig>Gærkoegaertenen-reereme, (S) kyrkogårdsförvaltning (sv)</orig>
  </e>
  <e>
    <lg>
      <l pos="N">infrastruktuvregoevtese</l>
    </lg>
    <tg lang="sv">
      <t pos="N">enheten för infrastruktur</t>
    </tg>
    <orig>Infrastruktuvregoevtese, (S) enheten för infrastruktur (sv)</orig>
  </e>
  <e>
    <lg>
      <l pos="N">komministere</l>
    </lg>
    <tg lang="sv">
      <t pos="N">komminister</t>
    </tg>
    <orig>Komministere, (S) komminister (sv)</orig>
  </e>
  <e>
    <lg>
      <l pos="N">kroeptekapeelle</l>
    </lg>
    <tg lang="sv">
      <t pos="N">gravkapell</t>
    </tg>
    <tg lang="nb">
      <t pos="N">gravkapell</t>
    </tg>
    <orig>Kroeptekapeelle, (S) gravkapell (nb), gravkapell (sv)</orig>
  </e>
  <e>
    <lg>
      <l pos="N">kroeptereerije</l>
    </lg>
    <tg lang="sv">
      <t pos="N">gravadministratör</t>
    </tg>
    <tg lang="nb">
      <t pos="N">gravforvalter</t>
    </tg>
    <orig>Kroeptereerije, (S) gravforvalter (nb), gravadministratör (sv)</orig>
  </e>
  <e>
    <lg>
      <l pos="N">kultuvreiktedæjja</l>
    </lg>
    <tg lang="sv">
      <t pos="N">kultursamordnare</t>
    </tg>
    <tg lang="nb">
      <t pos="N">kulturkoordinator</t>
    </tg>
    <orig>Kultuvreiktedæjja, (S) kulturkoordinator (nb), kultursamordnare (sv)</orig>
  </e>
  <e>
    <lg>
      <l pos="Phrase">kultuvreskuvlen åejvie</l>
    </lg>
    <tg lang="sv">
      <t pos="Phrase">kulturskoleschef</t>
    </tg>
    <tg lang="nb">
      <t pos="Phrase">kulturskolesjef</t>
    </tg>
    <orig>Kultuvreskuvlen åejvie, (S) kulturskolesjef (nb), kulturskoleschef (sv)</orig>
  </e>
  <e>
    <lg>
      <l pos="Phrase">kultuvreskuvlen åvtehke</l>
    </lg>
    <tg lang="nb">
      <t pos="Phrase">leder for kulturskoler</t>
    </tg>
    <orig>Kultuvreskuvlen åvtehke, (S) leder for kulturskoler (nb)</orig>
  </e>
  <e>
    <lg>
      <l pos="N">kvaliteete-evtiedæjja</l>
    </lg>
    <tg lang="sv">
      <t pos="N">kvalitetsutvecklare</t>
    </tg>
    <orig>Kvaliteete-evtiedæjja, (S) kvalitetsutvecklare (sv)</orig>
  </e>
  <e>
    <lg>
      <l pos="N">laantearkitekte</l>
    </lg>
    <tg lang="sv">
      <t pos="N">landskapsarkitekt</t>
    </tg>
    <orig>Laantearkitekte, (S) landskapsarkitekt (sv)</orig>
  </e>
  <e>
    <lg>
      <l pos="Phrase">laavkoe jïh eejehtslehkie</l>
    </lg>
    <tg lang="sv">
      <t pos="Phrase">bad och camping</t>
    </tg>
    <tg lang="nb">
      <t pos="Phrase">bad og camping</t>
    </tg>
    <orig>Laavkoe jïh eejehtslehkie, (S) bad og camping (nb), bad och camping (sv)</orig>
  </e>
  <e>
    <lg>
      <l pos="N">leahpadongkeme</l>
    </lg>
    <tg lang="sv">
      <t pos="N">biljettexpedition</t>
    </tg>
    <tg lang="nb">
      <t pos="N">billettbestilling</t>
    </tg>
    <orig>Leahpadongkeme, (S) billettbestilling (nb) biljettexpedition (sv)</orig>
  </e>
  <e>
    <lg>
      <l pos="N">lientsiendajve</l>
    </lg>
    <tg lang="nb">
      <t pos="N">lensmannsdistrikt</t>
    </tg>
    <orig>Lientsiendajve, (S) lensmannsdistrikt (nb)</orig>
  </e>
  <e>
    <lg>
      <l pos="N">lientsiengaertene</l>
    </lg>
    <tg lang="nb">
      <l_ref>lientsiengåetie_n</l_ref>
      <t pos="N">lensmannsgård</t>
    </tg>
    <orig>Lientsiengåetie, lientsiengaertene, (S) lensmannsgård (nb)</orig>
  </e>
  <e>
    <lg>
      <l pos="N">lientsiengåetie</l>
    </lg>
    <tg lang="nb">
      <l_ref>lientsiengaertene_n</l_ref>
      <t pos="N">lensmannsgård</t>
    </tg>
    <orig>Lientsiengåetie, lientsiengaertene, (S) lensmannsgård (nb)</orig>
  </e>
  <e>
    <lg>
      <l pos="N">lientsienkontovre</l>
    </lg>
    <tg lang="nb">
      <t pos="N">lensmannskontor</t>
    </tg>
    <orig>Lientsienkontovre, (S) lensmannskontor (nb)</orig>
  </e>
  <e>
    <lg>
      <l pos="N">lïhkesadtje</l>
    </lg>
    <tg lang="nb">
      <t pos="N">pårørende</t>
    </tg>
    <tg lang="sv">
      <t pos="N">anhörig</t>
    </tg>
    <orig>Lïhkesadtje, (S) Anhörig (sv) pårørende (nb)</orig>
  </e>
  <e>
    <lg>
      <l pos="N">lïhkesadtjedåarjoe</l>
    </lg>
    <tg lang="sv">
      <t pos="N">anhörigstöd</t>
    </tg>
    <tg lang="nb">
      <t pos="N">pårørendestøtte</t>
    </tg>
    <orig>Lïhkesadtjedåarjoe, (S) pårørendestøtte (nb) anhörigstöd (sv)</orig>
  </e>
  <e>
    <lg>
      <l pos="Phrase">maanaj- jïh fuelhkiengoevtese</l>
    </lg>
    <tg lang="sv">
      <t pos="Phrase">enheten för barn och familj</t>
    </tg>
    <orig>Maanaj- jïh fuelhkiengoevtese, (S) enheten för barn och familj (sv)</orig>
  </e>
  <e>
    <lg>
      <l pos="N">njuenehke</l>
    </lg>
    <tg lang="nb">
      <t pos="N">ledelse</t>
    </tg>
    <tg lang="sv">
      <t pos="N">ledning</t>
    </tg>
    <orig>Njuenehke, (S) ledning (sv), ledelse (nb)</orig>
  </e>
  <e>
    <lg>
      <l pos="N">njuenehksdåehkie</l>
    </lg>
    <tg lang="sv">
      <t pos="N">ledningsgrupp</t>
    </tg>
    <orig>Njuenehksdåehkie, (S) ledningsgrupp (sv)</orig>
  </e>
  <e>
    <lg>
      <l pos="N">paehperepaantje</l>
    </lg>
    <tg lang="sv">
      <t pos="N">pappersförpackning</t>
    </tg>
    <tg lang="nb">
      <t pos="N">papiremballasje</t>
    </tg>
    <orig>Paehperepaantje, (S) papiremballasje (nb), pappersförpackning (sv)</orig>
  </e>
  <e>
    <lg>
      <l pos="N">plaastepaantje</l>
    </lg>
    <tg lang="sv">
      <t pos="N">plastförpackning</t>
    </tg>
    <tg lang="nb">
      <t pos="N">plastemballasje</t>
    </tg>
    <orig>Plaastepaantje, (S) plastemballasje (nb), plastförpackning (sv)</orig>
  </e>
  <e>
    <lg>
      <l pos="Phrase">reereles iktedæjja</l>
    </lg>
    <tg lang="sv">
      <t pos="Phrase">administrativ samordnare</t>
    </tg>
    <orig>Reereles iktedæjja, (S) administrativ samordnare (sv)</orig>
  </e>
  <e>
    <lg>
      <l pos="Phrase">reereles reerije</l>
    </lg>
    <tg lang="sv">
      <t pos="Phrase">administrativ förvaltare</t>
    </tg>
    <tg lang="sv">
      <t pos="Phrase">administrativ korrdinator</t>
    </tg>
    <tg lang="nb">
      <t pos="Phrase">administrativ korrdinator</t>
    </tg>
    <orig>Reereles reerije, (S) administrativ korrdinator (nb), administrativ förvaltare, administrativ korrdinator (sv)</orig>
  </e>
  <e>
    <lg>
      <l pos="N">reereme-moenehtse</l>
    </lg>
    <tg lang="sv">
      <t pos="N">förvaltnings kommitè</t>
    </tg>
    <tg lang="nb">
      <t pos="N">administrasjonsutvalg</t>
    </tg>
    <orig>Reereme-moenehtse, (S) administrasjonsutvalg (nb), förvaltnings kommitè (sv)</orig>
  </e>
  <e>
    <lg>
      <l pos="Phrase">særteldh maanaj goevtese</l>
    </lg>
    <tg lang="sv">
      <l_ref>sarteldh_maanaj_goevtese_phrase</l_ref>
      <t pos="Phrase">enheten for placerade barn</t>
    </tg>
    <orig>Sarteldh maanaj goevtese, særteldh maanaj goevtese, (S) enheten for placerade barn (sv)</orig>
  </e>
  <e>
    <lg>
      <l pos="Phrase">sarteldh maanaj goevtese</l>
    </lg>
    <tg lang="sv">
      <l_ref>særteldh_maanaj_goevtese_phrase</l_ref>
      <t pos="Phrase">enheten for placerade barn</t>
    </tg>
    <orig>Sarteldh maanaj goevtese, særteldh maanaj goevtese, (S) enheten for placerade barn (sv)</orig>
  </e>
  <e>
    <lg>
      <l pos="N">soptsestallemetjïehtjele</l>
    </lg>
    <tg lang="sv">
      <t pos="N">samtalsrum</t>
    </tg>
    <tg lang="nb">
      <t pos="N">samtalerom</t>
    </tg>
    <orig>Soptsestallemetjïehtjele, (S) samtalerom (nb), samtalsrum (sv)</orig>
  </e>
  <e>
    <lg>
      <l pos="N">svihtjemeheaptoe</l>
    </lg>
    <tg lang="sv">
      <t pos="N">funktionsnedsättning</t>
    </tg>
    <tg lang="nb">
      <t pos="N">funksjonshemning</t>
    </tg>
    <tg lang="nb">
      <t pos="N">fuksjonsnedsettelse</t>
    </tg>
    <orig>Svihtjemeheaptoe, (S) funksjonshemning, fuksjonsnedsettelse (nb), funktionsnedsättning (sv)</orig>
  </e>
  <e>
    <lg>
      <l pos="N">såaknehearra</l>
    </lg>
    <tg lang="nb">
      <t pos="N">sogneprest</t>
    </tg>
    <tg lang="sv">
      <t pos="N">kyrkoherde</t>
    </tg>
    <orig>Såaknehearra, (S) kyrkoherde (sv) sogneprest (nb)</orig>
  </e>
  <e>
    <lg>
      <l pos="N">vierhkiesijjiebarkije</l>
    </lg>
    <tg lang="sv">
      <t pos="N">verkstadsarbetare</t>
    </tg>
    <tg lang="nb">
      <t pos="N">verkstedarbeider</t>
    </tg>
    <orig>Vierhkiesijjiebarkije, (S) verkstedarbeider (nb) verkstadsarbetare (sv)</orig>
  </e>
  <e>
    <lg>
      <l pos="N">våarhkoedirektööre</l>
    </lg>
    <tg lang="nb">
      <t pos="N">arkivdirektør</t>
    </tg>
    <orig>Våarhkoedirektööre, (S) arkivdirektør (nb)</orig>
  </e>
  <e>
    <lg>
      <l pos="N">våarhkoeklahke</l>
    </lg>
    <tg lang="sv">
      <t pos="N">arkivassistent</t>
    </tg>
    <tg lang="nb">
      <t pos="N">arkivassistent</t>
    </tg>
    <orig>Våarhkoeklahke, (S) arkivassistent (nb), arkivassistent (sv)</orig>
  </e>
  <e>
    <lg>
      <l pos="N">våarhkoe-åvtehke</l>
    </lg>
    <tg lang="sv">
      <t pos="N">arkivföreståndare</t>
    </tg>
    <tg lang="nb">
      <t pos="N">arkivleder</t>
    </tg>
    <orig>Våarhkoe-åvtehke, (S) arkivleder (nb), arkivföreståndare (sv)</orig>
  </e>
  <e>
    <lg>
      <l pos="N">ööhpehtimmiereereme</l>
    </lg>
    <tg lang="sv">
      <t pos="N">bildningsförvaltningen</t>
    </tg>
    <tg lang="sv">
      <t pos="N">utbildningsförvaltningen</t>
    </tg>
    <orig>Ööhpehtimmiereereme, (S) bildningsförvaltningen, utbildningsförvaltningen (sv)</orig>
  </e>
  <e>
    <lg>
      <l pos="Phrase">aejlies voejkene</l>
    </lg>
    <tg lang="sv">
      <t pos="Phrase">den heliga ande</t>
    </tg>
    <tg lang="nb">
      <t pos="Phrase">den hellige ånd</t>
    </tg>
    <orig>Aejlies Voejkene, (MWE) Den Hellige Ånd (nb), Den Heliga Ande (sv)</orig>
  </e>
  <e>
    <lg>
      <l pos="N">aejlieskodtje</l>
    </lg>
    <tg lang="nb">
      <t pos="N">hellig person</t>
    </tg>
    <tg lang="nb">
      <t pos="N">helgen</t>
    </tg>
    <orig>Aejlieskodtje, (S) hellig person, helgen (nb)</orig>
  </e>
  <e>
    <lg>
      <l pos="N">aejliesvoete</l>
    </lg>
    <tg lang="nb">
      <t pos="N">hellighet</t>
    </tg>
    <orig>Aejliesvoete, (S) hellighet (nb)</orig>
  </e>
  <e>
    <lg>
      <l pos="N">aejverdsvuelie</l>
    </lg>
    <tg lang="nb">
      <t pos="N">klagemelodi</t>
    </tg>
    <tg lang="nb">
      <t pos="N">klagesang</t>
    </tg>
    <orig>Aejverdsvuelie, (S) klagemelodi, klagesang (nb)</orig>
  </e>
  <e>
    <lg>
      <l pos="Phrase">aevhkehts (attr) aevhkehth (pred)</l>
    </lg>
    <tg lang="nb">
      <t pos="Phrase">nyttesløs</t>
    </tg>
    <tg lang="nb">
      <t pos="Phrase">nytteløst</t>
    </tg>
    <tg lang="nb">
      <t pos="Phrase">forgjeves</t>
    </tg>
    <tg lang="nb">
      <t pos="Phrase">til ingen nytte</t>
    </tg>
    <tg lang="nb">
      <t pos="Phrase">unyttig</t>
    </tg>
    <tg lang="nb">
      <t pos="Phrase">gagnløst</t>
    </tg>
    <orig>Aevhkehts (attr) aevhkehth (pred), (A) nyttesløs, nytteløst, forgjeves, til ingen nytte, unyttig, gagnløst (nb)</orig>
  </e>
  <e>
    <lg>
      <l pos="Phrase">laagne låedtjie</l>
    </lg>
    <tg lang="sv">
      <l_ref>låedtjie_n</l_ref>
      <t pos="Phrase">lugnt</t>
    </tg>
    <tg lang="nb">
      <l_ref>låedtjie_n</l_ref>
      <t pos="Phrase">stille</t>
    </tg>
    <orig>Laagne låedtjie, låedtjie, (S) stille (nb) lugnt (sv)</orig>
  </e>
  <e>
    <lg>
      <l pos="N">låedtjie</l>
    </lg>
    <tg lang="sv">
      <l_ref>laagne_låedtjie_phrase</l_ref>
      <t pos="N">lugnt</t>
    </tg>
    <tg lang="nb">
      <l_ref>laagne_låedtjie_phrase</l_ref>
      <t pos="N">stille</t>
    </tg>
    <orig>Laagne låedtjie, låedtjie, (S) stille (nb) lugnt (sv)</orig>
  </e>
  <e>
    <lg>
      <l pos="N">tjuvjie</l>
    </lg>
    <tg lang="sv">
      <l_ref>hïevjebïegke_n</l_ref>
      <t pos="N">bris</t>
    </tg>
    <tg lang="sv">
      <l_ref>hïevjebïegke_n</l_ref>
      <t pos="N">svag vind</t>
    </tg>
    <tg lang="nb">
      <l_ref>hïevjebïegke_n</l_ref>
      <t pos="N">flau vind</t>
    </tg>
    <orig>Hïevjebïegke, tjuvjie, (S) flau vind (nb), bris, svag vind (sv)</orig>
  </e>
  <e>
    <lg>
      <l pos="N">hïevjebïegke</l>
    </lg>
    <tg lang="sv">
      <l_ref>tjuvjie_n</l_ref>
      <t pos="N">bris</t>
    </tg>
    <tg lang="sv">
      <l_ref>tjuvjie_n</l_ref>
      <t pos="N">svag vind</t>
    </tg>
    <tg lang="nb">
      <l_ref>tjuvjie_n</l_ref>
      <t pos="N">flau vind</t>
    </tg>
    <orig>Hïevjebïegke, tjuvjie, (S) flau vind (nb), bris, svag vind (sv)</orig>
  </e>
  <e>
    <lg>
      <l pos="N">jïele</l>
    </lg>
    <tg lang="sv">
      <l_ref>asve_n</l_ref>
      <t pos="N">bris</t>
    </tg>
    <tg lang="sv">
      <l_ref>asve_n</l_ref>
      <t pos="N">svag vind</t>
    </tg>
    <tg lang="nb">
      <l_ref>asve_n</l_ref>
      <t pos="N">kald svak vind</t>
    </tg>
    <orig>Jïele, asve, (S) kald svak vind (nb), bris, svag vind (sv)</orig>
  </e>
  <e>
    <lg>
      <l pos="N">asve</l>
    </lg>
    <tg lang="sv">
      <l_ref>jïele_n</l_ref>
      <t pos="N">bris</t>
    </tg>
    <tg lang="sv">
      <l_ref>jïele_n</l_ref>
      <t pos="N">svag vind</t>
    </tg>
    <tg lang="nb">
      <l_ref>jïele_n</l_ref>
      <t pos="N">kald svak vind</t>
    </tg>
    <orig>Jïele, asve, (S) kald svak vind (nb), bris, svag vind (sv)</orig>
  </e>
  <e>
    <lg>
      <l pos="N">raepkie</l>
    </lg>
    <tg lang="sv">
      <t pos="N">bris</t>
    </tg>
    <tg lang="sv">
      <t pos="N">måttlig vind</t>
    </tg>
    <tg lang="nb">
      <t pos="N">lett bris</t>
    </tg>
    <orig>Raepkie, (S) lett bris (nb), bris, måttlig vind (sv)</orig>
  </e>
  <e>
    <lg>
      <l pos="N">bïegke</l>
    </lg>
    <tg lang="sv">
      <t pos="N">bris</t>
    </tg>
    <tg lang="sv">
      <t pos="N">måttlig vind</t>
    </tg>
    <tg lang="nb">
      <t pos="N">laber bris</t>
    </tg>
    <orig>Bïegke, (S) laber bris (nb), bris, måttlig vind (sv)</orig>
  </e>
  <e>
    <lg>
      <l pos="Phrase">garre bïegke</l>
    </lg>
    <tg lang="sv">
      <t pos="Phrase">bris</t>
    </tg>
    <tg lang="sv">
      <t pos="Phrase">frisk vind</t>
    </tg>
    <tg lang="nb">
      <t pos="Phrase">frisk bris</t>
    </tg>
    <orig>Garre bïegke, (MWE) frisk bris (nb), bris , frisk vind (sv)</orig>
  </e>
  <e>
    <lg>
      <l pos="Phrase">træjpas bïegke</l>
    </lg>
    <tg lang="sv">
      <t pos="Phrase">bris</t>
    </tg>
    <tg lang="sv">
      <t pos="Phrase">frisk vind</t>
    </tg>
    <tg lang="nb">
      <t pos="Phrase">liten kuling</t>
    </tg>
    <orig>Træjpas bïegke, (MWE) liten kuling (nb), bris, frisk vind (sv)</orig>
  </e>
  <e>
    <lg>
      <l pos="N">rapke</l>
    </lg>
    <tg lang="sv">
      <l_ref>fropmehke_n</l_ref>
      <t pos="N">hård vind</t>
    </tg>
    <tg lang="sv">
      <l_ref>fropmehke_n</l_ref>
      <t pos="N">kuling</t>
    </tg>
    <tg lang="nb">
      <l_ref>fropmehke_n</l_ref>
      <t pos="N">stiv kuling</t>
    </tg>
    <orig>Fropmehke, Rapke, (S) stiv kuling (nb), hård vind, kuling (sv)</orig>
  </e>
  <e>
    <lg>
      <l pos="N">fropmehke</l>
    </lg>
    <tg lang="sv">
      <l_ref>rapke_n</l_ref>
      <t pos="N">hård vind</t>
    </tg>
    <tg lang="sv">
      <l_ref>rapke_n</l_ref>
      <t pos="N">kuling</t>
    </tg>
    <tg lang="nb">
      <l_ref>rapke_n</l_ref>
      <t pos="N">stiv kuling</t>
    </tg>
    <orig>Fropmehke, Rapke, (S) stiv kuling (nb), hård vind, kuling (sv)</orig>
  </e>
  <e>
    <lg>
      <l pos="Phrase">garre rapke</l>
    </lg>
    <tg lang="sv">
      <l_ref>garre_fropmehke_phrase</l_ref>
      <t pos="Phrase">hård vind</t>
    </tg>
    <tg lang="sv">
      <l_ref>garre_fropmehke_phrase</l_ref>
      <t pos="Phrase">kuling</t>
    </tg>
    <tg lang="nb">
      <l_ref>garre_fropmehke_phrase</l_ref>
      <t pos="Phrase">sterk kuling</t>
    </tg>
    <orig>Garre fropmehke, garre rapke, (MWE) sterk kuling (nb), hård vind, kuling (sv)</orig>
  </e>
  <e>
    <lg>
      <l pos="Phrase">garre fropmehke</l>
    </lg>
    <tg lang="sv">
      <l_ref>garre_rapke_phrase</l_ref>
      <t pos="Phrase">hård vind</t>
    </tg>
    <tg lang="sv">
      <l_ref>garre_rapke_phrase</l_ref>
      <t pos="Phrase">kuling</t>
    </tg>
    <tg lang="nb">
      <l_ref>garre_rapke_phrase</l_ref>
      <t pos="Phrase">sterk kuling</t>
    </tg>
    <orig>Garre fropmehke, garre rapke, (MWE) sterk kuling (nb), hård vind, kuling (sv)</orig>
  </e>
  <e>
    <lg>
      <l pos="N">bïegke-elmie</l>
    </lg>
    <tg lang="sv">
      <l_ref>gaajh_elmie_phrase</l_ref>
      <l_ref>elmie_n</l_ref>
      <t pos="N">hård vind</t>
    </tg>
    <tg lang="sv">
      <l_ref>gaajh_elmie_phrase</l_ref>
      <l_ref>elmie_n</l_ref>
      <t pos="N">kuling</t>
    </tg>
    <tg lang="nb">
      <l_ref>gaajh_elmie_phrase</l_ref>
      <l_ref>elmie_n</l_ref>
      <t pos="N">liten storm</t>
    </tg>
    <orig>Gaajh elmie, Elmie, bïegke-elmie, (S), liten storm (nb), hård vind, kuling (sv)</orig>
  </e>
  <e>
    <lg>
      <l pos="Phrase">gaajh elmie</l>
    </lg>
    <tg lang="sv">
      <l_ref>bïegke-elmie_n</l_ref>
      <l_ref>elmie_n</l_ref>
      <t pos="Phrase">hård vind</t>
    </tg>
    <tg lang="sv">
      <l_ref>bïegke-elmie_n</l_ref>
      <l_ref>elmie_n</l_ref>
      <t pos="Phrase">kuling</t>
    </tg>
    <tg lang="nb">
      <l_ref>bïegke-elmie_n</l_ref>
      <l_ref>elmie_n</l_ref>
      <t pos="Phrase">liten storm</t>
    </tg>
    <orig>Gaajh elmie, Elmie, bïegke-elmie, (S), liten storm (nb), hård vind, kuling (sv)</orig>
  </e>
  <e>
    <lg>
      <l pos="N">elmie</l>
    </lg>
    <tg lang="sv">
      <l_ref>bïegke-elmie_n</l_ref>
      <l_ref>gaajh_elmie_phrase</l_ref>
      <t pos="N">hård vind</t>
    </tg>
    <tg lang="sv">
      <l_ref>bïegke-elmie_n</l_ref>
      <l_ref>gaajh_elmie_phrase</l_ref>
      <t pos="N">kuling</t>
    </tg>
    <tg lang="nb">
      <l_ref>bïegke-elmie_n</l_ref>
      <l_ref>gaajh_elmie_phrase</l_ref>
      <t pos="N">liten storm</t>
    </tg>
    <orig>Gaajh elmie, Elmie, bïegke-elmie, (S), liten storm (nb), hård vind, kuling (sv)</orig>
  </e>
  <e>
    <lg>
      <l pos="N">træjpoe</l>
    </lg>
    <tg lang="sv">
      <t pos="N">storm</t>
    </tg>
    <tg lang="nb">
      <t pos="N">full storm</t>
    </tg>
    <orig>Træjpoe, (S) full storm (nb) storm (sv)</orig>
  </e>
  <e>
    <lg>
      <l pos="N">værtoe</l>
    </lg>
    <tg lang="sv">
      <t pos="N">storm</t>
    </tg>
    <tg lang="nb">
      <t pos="N">sterk storm</t>
    </tg>
    <orig>Værtoe, (S) sterk storm (nb) storm (sv)</orig>
  </e>
  <e>
    <lg>
      <l pos="N">tjoelmehke</l>
    </lg>
    <tg lang="sv">
      <l_ref>garre_værtoe_phrase</l_ref>
      <l_ref>orkaane_n</l_ref>
      <t pos="N">orkan</t>
    </tg>
    <tg lang="nb">
      <l_ref>garre_værtoe_phrase</l_ref>
      <l_ref>orkaane_n</l_ref>
      <t pos="N">orkan</t>
    </tg>
    <orig>Garre værtoe, tjoelmehke, Orkaane, (S) orkan (nb) orkan (sv)</orig>
  </e>
  <e>
    <lg>
      <l pos="Phrase">garre værtoe</l>
    </lg>
    <tg lang="sv">
      <l_ref>tjoelmehke_n</l_ref>
      <l_ref>orkaane_n</l_ref>
      <t pos="Phrase">orkan</t>
    </tg>
    <tg lang="nb">
      <l_ref>tjoelmehke_n</l_ref>
      <l_ref>orkaane_n</l_ref>
      <t pos="Phrase">orkan</t>
    </tg>
    <orig>Garre værtoe, tjoelmehke, Orkaane, (S) orkan (nb) orkan (sv)</orig>
  </e>
  <e>
    <lg>
      <l pos="N">orkaane</l>
    </lg>
    <tg lang="sv">
      <l_ref>tjoelmehke_n</l_ref>
      <l_ref>garre_værtoe_phrase</l_ref>
      <t pos="N">orkan</t>
    </tg>
    <tg lang="nb">
      <l_ref>tjoelmehke_n</l_ref>
      <l_ref>garre_værtoe_phrase</l_ref>
      <t pos="N">orkan</t>
    </tg>
    <orig>Garre værtoe, tjoelmehke, Orkaane, (S) orkan (nb) orkan (sv)</orig>
  </e>
</r>
